mcp_server_rewind/__init__.py
mcp_server_rewind/__main__.py
mcp_server_rewind/models.py
mcp_server_rewind/server.py
mcp_server_rewind/transcript_reader.py
mcp_server_rewind-0.1.0.dist-info/METADATA
mcp_server_rewind-0.1.0.dist-info/WHEEL
mcp_server_rewind-0.1.0.dist-info/entry_points.txt
mcp_server_rewind-0.1.0.dist-info/RECORD
