Metadata-Version: 2.4
Name: mcp-server-rewind
Version: 0.1.0
Summary: A Model Context Protocol server for querying Rewind AI screen recording transcripts
Author: Pascal Wichmann
License: MIT
Keywords: llm,mcp,rewind,screen-recording,transcripts
Classifier: Development Status :: 4 - Beta
Classifier: Intended Audience :: Developers
Classifier: License :: OSI Approved :: MIT License
Classifier: Programming Language :: Python :: 3
Classifier: Programming Language :: Python :: 3.10
Classifier: Programming Language :: Python :: 3.11
Classifier: Programming Language :: Python :: 3.12
Requires-Python: >=3.10
Requires-Dist: click>=8.1.7
Requires-Dist: mcp>=1.0.0
Requires-Dist: pydantic>=2.0.0
Requires-Dist: python-dotenv>=1.0.0
